biomarker_nlp/__init__.py
biomarker_nlp/biomarker_extraction.py
biomarker_nlp/negation_cue_scope.py
biomarker_nlp/negation_negbert.py
biomarker_nlp-0.0.4.dist-info/LICENSE
biomarker_nlp-0.0.4.dist-info/METADATA
biomarker_nlp-0.0.4.dist-info/WHEEL
biomarker_nlp-0.0.4.dist-info/top_level.txt
biomarker_nlp-0.0.4.dist-info/RECORD
