Metadata-Version: 2.1
Name: biomarker-nlp
Version: 0.0.4
Summary: NLP for detecting and extracting biomarkers from biomedical text
Home-page: https://github.com/Damonlin11/FDA-approved-Targeted-Therapies-Label-Extraction/tree/main/biomarker_nlp
Author: Junxia Lin
Author-email: damonlin11@gmail.com
License: UNKNOWN
Project-URL: Bug Tracker, https://github.com/Damonlin11/FDA-approved-Targeted-Therapies-Label-Extraction/issues
Project-URL: Documentation, https://github.com/Damonlin11/FDA-approved-Targeted-Therapies-Label-Extraction/blob/main/biomarker_nlp/docs/_build/latex/biomarker_nlp.pdf
Platform: UNKNOWN
Classifier: Programming Language :: Python :: 3
Classifier: License :: OSI Approved :: MIT License
Classifier: Operating System :: OS Independent
Requires-Python: >=3.6
License-File: LICENSE
